{
    "@class": "com.kony.gen.viz.model.component.KVizCamera",
    "DNDConfig": null,
    "__parentReadjusting__": false,
    "_height_": {
        "type": "string",
        "value": "100%"
    },
    "_left_": {
        "type": "string",
        "value": "0dp"
    },
    "_margin_": [
        0,
        0,
        0,
        0
    ],
    "_padding_": [
        0,
        0,
        0,
        0
    ],
    "_skin_": "s56887b52e41453cbac7c480ed6c3f07",
    "_text_": "",
    "_top_": {
        "type": "string",
        "value": "0dp"
    },
    "_width_": {
        "type": "string",
        "value": "100%"
    },
    "canUpdateUI": true,
    "containerweight": 100,
    "contentalignment": 5,
    "desktopweb": {
        "render": false
    },
    "id": "Camera1",
    "info": null,
    "isvisible": true,
    "kuid": "ac4412050ade4e74a61a25c19b27b8da",
    "name": "kony.ui.Camera",
    "oncapture": "AS_Camera_e26ec0ce958b49fa80d62efead0a477c",
    "parent": "cameraContainer",
    "pf": "Map1",
    "spaan": {
        "render": false
    },
    "spaandroidtablet": {
        "render": false
    },
    "spabb": {
        "render": false
    },
    "spaip": {
        "render": false
    },
    "spaipad": {
        "render": false
    },
    "spawindowstablet": {
        "render": false
    },
    "spawinphone8": {
        "render": false
    },
    "wType": "Camera",
    "watchos": {
        "render": false
    },
    "zindex": 1
}